gouba.py
gouba-1.0.0.dist-info/METADATA
gouba-1.0.0.dist-info/WHEEL
gouba-1.0.0.dist-info/entry_points.txt
gouba-1.0.0.dist-info/top_level.txt
gouba-1.0.0.dist-info/RECORD
