Metadata-Version: 2.1
Name: gouba
Version: 1.0.0
Summary: The SouGou Searcher On Python|Python 搜狗搜索工具
Home-page: UNKNOWN
Author: Python学霸
Author-email: python@xueba.com
License: UNKNOWN
Platform: UNKNOWN
Requires-Dist: mechanicalsoup
